pyyoutube/__init__.py
pyyoutube/__version__.py
pyyoutube/api.py
pyyoutube/client.py
pyyoutube/error.py
pyyoutube/media.py
pyyoutube/models/__init__.py
pyyoutube/models/activity.py
pyyoutube/models/auth.py
pyyoutube/models/base.py
pyyoutube/models/caption.py
pyyoutube/models/category.py
pyyoutube/models/channel.py
pyyoutube/models/channel_banner.py
pyyoutube/models/channel_section.py
pyyoutube/models/comment.py
pyyoutube/models/comment_thread.py
pyyoutube/models/common.py
pyyoutube/models/i18n.py
pyyoutube/models/member.py
pyyoutube/models/memberships_level.py
pyyoutube/models/mixins.py
pyyoutube/models/playlist.py
pyyoutube/models/playlist_item.py
pyyoutube/models/search_result.py
pyyoutube/models/subscription.py
pyyoutube/models/video.py
pyyoutube/models/video_abuse_report_reason.py
pyyoutube/models/watermark.py
pyyoutube/resources/__init__.py
pyyoutube/resources/activities.py
pyyoutube/resources/base_resource.py
pyyoutube/resources/captions.py
pyyoutube/resources/channel_banners.py
pyyoutube/resources/channel_sections.py
pyyoutube/resources/channels.py
pyyoutube/resources/comment_threads.py
pyyoutube/resources/comments.py
pyyoutube/resources/i18n_languages.py
pyyoutube/resources/i18n_regions.py
pyyoutube/resources/members.py
pyyoutube/resources/membership_levels.py
pyyoutube/resources/playlist_items.py
pyyoutube/resources/playlists.py
pyyoutube/resources/search.py
pyyoutube/resources/subscriptions.py
pyyoutube/resources/thumbnails.py
pyyoutube/resources/video_abuse_report_reasons.py
pyyoutube/resources/video_categories.py
pyyoutube/resources/videos.py
pyyoutube/resources/watermarks.py
pyyoutube/utils/__init__.py
pyyoutube/utils/constants.py
pyyoutube/utils/params_checker.py
pyyoutube/youtube_utils.py
python_youtube-0.9.8.dist-info/LICENSE
python_youtube-0.9.8.dist-info/METADATA
python_youtube-0.9.8.dist-info/WHEEL
python_youtube-0.9.8.dist-info/RECORD
